swissparlpy/__init__.py
swissparlpy/client.py
swissparlpy/errors.py
swissparlpy-0.3.0.dist-info/LICENSE.md
swissparlpy-0.3.0.dist-info/WHEEL
swissparlpy-0.3.0.dist-info/METADATA
swissparlpy-0.3.0.dist-info/RECORD
