Metadata-Version: 2.1
Name: swissparlpy
Version: 0.3.0
Summary: Client for Swiss parliament API
Author-email: Stefan Oderbolz <odi@metaodi.ch>
Requires-Python: >=3.7
Classifier: License :: OSI Approved :: MIT License
Requires-Dist: requests
Requires-Dist: pyodata>=1.10.0
Requires-Dist: flit ; extra == "dev"
Requires-Dist: jupyter ; extra == "dev"
Requires-Dist: pandas ; extra == "dev"
Requires-Dist: black ; extra == "dev"
Requires-Dist: pre-commit ; extra == "dev"
Requires-Dist: flake8 ; extra == "test"
Requires-Dist: mock ; extra == "test"
Requires-Dist: responses ; extra == "test"
Requires-Dist: pytest ; extra == "test"
Requires-Dist: pytest-cov ; extra == "test"
Project-URL: Home, https://github.com/metaodi/swissparlpy
Provides-Extra: dev
Provides-Extra: test
